{
  "version": "v1",
  "country": "España",
  "label": "Inventario premium de estaciones · España",
  "status": "active",
  "service_level": "L2",
  "coverage_level": "Catálogo georreferenciado oficial · España",
  "source_priority": "official_primero_con_fallback_abierto_trazable",
  "last_verified_at": "2026-03-11",
  "catalog_count": 3,
  "station_count": 2191,
  "hydrological_official_count": 2191,
  "station_count_note": "2191 estaciones oficiales georreferenciadas del Anuario de Aforos 2020-21.",
  "summary_note": "AquaRisk integra un catálogo georreferenciado oficial de 2191 estaciones hidrológicas de MITECO (SAIH-ROEA 2020-21). El WMS oficial sigue disponible como apoyo visual y de verificación.",
  "operator_counts": {
    "Augas de Galicia · Xunta de Galicia": 51,
    "C.H. Duero": 266,
    "C.H. Ebro": 497,
    "C.H. Guadalquivir": 220,
    "C.H. Guadiana": 209,
    "C.H. Segura": 180,
    "C.H. Tajo": 317,
    "MITECO / organismo no identificado": 451
  },
  "status_counts": {
    "histórica": 713,
    "operativa": 1478
  },
  "station_type_counts": {
    "Conducción": 219,
    "Embalse": 390,
    "Estación evaporimétrica": 91,
    "Estación hidrológica": 1491
  },
  "province_counts": {
    "albacete": 3,
    "Albacete": 53,
    "ALBACETE": 1,
    "Alicante": 52,
    "ALICANTE": 5,
    "Almería": 1,
    "Asturias": 68,
    "ASTURIAS": 3,
    "Badajoz": 97,
    "BADAJOZ": 2,
    "Burgos": 42,
    "BURGOS": 2,
    "Cantabria": 29,
    "CANTABRIA": 4,
    "Ceuta": 1,
    "Ciudad Real": 62,
    "Cuenca": 37,
    "CUENCA": 4,
    "España": 532,
    "EXTREMADURA": 1,
    "Girona": 4,
    "Granada": 44,
    "GRANADA": 3,
    "Guadalajara": 48,
    "GUADALAJARA": 3,
    "Guadalajara y Cuenca": 1,
    "Huelva": 22,
    "Huesca": 105,
    "HUESCA": 5,
    "La Rioja": 28,
    "LA RIOJA": 1,
    "LLEIDA": 1,
    "Lugo": 43,
    "LUGO": 8,
    "Madrid": 100,
    "MADRID": 1,
    "Murcia": 94,
    "MURCIA": 10,
    "Navarra": 58,
    "NAVARRA": 16,
    "OURENSE": 3,
    "Ourense / Orense": 44,
    "Palencia": 41,
    "Pontevedra": 12,
    "PONTEVEDRA": 12,
    "Salamanca": 38,
    "Segovia": 25,
    "SEGOVIA": 1,
    "Sevilla": 37,
    "SEVILLA": 8,
    "Soria": 22,
    "SORIA": 1,
    "Tarragona": 16,
    "TARRAGONA": 2,
    "Teruel": 53,
    "Toledo": 59,
    "Valencia": 69,
    "Valladolid": 21,
    "Vizcaya / Bizkaia": 9,
    "Zamora": 37,
    "Zaragoza": 84,
    "ZARAGOZA": 3
  },
  "suggested_view": {
    "center": {
      "lat": 39.800234,
      "lon": -3.62879
    },
    "zoom": 6,
    "bounds": {
      "minLon": -9.190758,
      "minLat": 35.896137,
      "maxLon": 1.933178,
      "maxLat": 43.70433
    }
  },
  "catalogs": [
    {
      "key": "meteorological_official",
      "label": "Estaciones meteorológicas oficiales",
      "operator": "AEMET",
      "status": "planned",
      "access_mode": "opendata_official",
      "service_level": "L1",
      "coverage_level": "Inventario premium en preparación",
      "station_count": null
    },
    {
      "key": "hydrological_official",
      "label": "Estaciones hidrológicas oficiales",
      "operator": "MITECO",
      "status": "active",
      "access_mode": "official_gml_wms",
      "service_level": "L2",
      "coverage_level": "Catálogo georreferenciado oficial activo · España",
      "station_count": 2191
    },
    {
      "key": "hydrological_operational_reference",
      "label": "Referencia operativa hidrológica",
      "operator": "MITECO / SAIH",
      "status": "planned",
      "access_mode": "official_support",
      "service_level": "L1",
      "coverage_level": "Referencia operativa en preparación",
      "station_count": null
    }
  ]
}
